dip/__init__.py
dip/_version.py
dip/client.py
dip/connection.py
dip/const.py
dip/errors.py
dip/pool.py
dip/proto.py
dip/server.py
deepfos_ipc-1.3.1.dist-info/METADATA
deepfos_ipc-1.3.1.dist-info/WHEEL
deepfos_ipc-1.3.1.dist-info/top_level.txt
deepfos_ipc-1.3.1.dist-info/RECORD
