Metadata-Version: 2.1
Name: deepfos-ipc
Version: 1.3.1
Summary: DeepFOS interprocess communication protocol
Home-page: 
Author: deepfos-python
Author-email: 'python@deepfos.com
Classifier: Development Status :: 3 - Alpha
Classifier: Intended Audience :: Developers
Classifier: Topic :: Software Development :: Libraries :: Python Modules
Classifier: Programming Language :: Python :: 3.8
Classifier: Programming Language :: Python :: 3.9
Classifier: Programming Language :: Python :: 3.10
Classifier: Operating System :: OS Independent
Requires-Python: >=3.8.3
Requires-Dist: loguru
